{"meta":{"currency":"AUD","symbol":"IMPQ.AX","exchangeName":"ASX","fullExchangeName":"ASX","instrumentType":"EQUITY","firstTradeDate":1558656000,"regularMarketTime":1758240086,"hasPrePostMarketData":false,"gmtoffset":36000,"timezone":"AEST","exchangeTimezoneName":"Australia\/Sydney","regularMarketPrice":5.1,"fiftyTwoWeekHigh":5.14,"fiftyTwoWeekLow":4.29,"regularMarketDayHigh":5.1,"regularMarketDayLow":5.07,"regularMarketVolume":9187,"longName":"Perennial Better Future Fund","shortName":"EIVST IMPQ TMF UNITS","chartPreviousClose":5.07,"priceHint":2,"currentTradingPeriod":{"pre":{"timezone":"AEST","end":1758240000,"start":1758229200,"gmtoffset":36000},"regular":{"timezone":"AEST","end":1758262320,"start":1758240000,"gmtoffset":36000},"post":{"timezone":"AEST","end":1758262320,"start":1758262320,"gmtoffset":36000}},"dataGranularity":"1d","range":"","validRanges":["1d","5d","1mo","3mo","6mo","1y","2y","5y","10y","ytd","max"]},"quote":{"1758153600":{"timestamp":1758153600,"date":"2025-09-18","open":5.03000020980835,"close":5.070000171661377,"adjclose":5.070000171661377,"low":5.03000020980835,"high":5.070000171661377,"volume":7148},"1758240086":{"timestamp":1758240086,"date":"2025-09-19","open":5.070000171661377,"close":5.099999904632568,"adjclose":5.099999904632568,"low":5.070000171661377,"high":5.099999904632568,"volume":9187}},"last_updated":1758240086}